deciphon_worker/__init__.py
deciphon_worker/alarm.py
deciphon_worker/batch.py
deciphon_worker/hmmer.py
deciphon_worker/interrupted.py
deciphon_worker/press.py
deciphon_worker/progressor.py
deciphon_worker/queue313.py
deciphon_worker/queue_loop.py
deciphon_worker/scanner.py
deciphon_worker/thread.py
deciphon_worker-0.5.4.dist-info/METADATA
deciphon_worker-0.5.4.dist-info/WHEEL
deciphon_worker-0.5.4.dist-info/RECORD
