Metadata-Version: 2.4
Name: deciphon-worker
Version: 0.5.4
Summary: Deciphon worker.
Author-email: Danilo Horta <danilo.horta@pm.me>
License-Expression: MIT
Requires-Python: ~=3.9
Requires-Dist: deciphon-core<2,>=1.0.17
Requires-Dist: deciphon-schema>=0.2.0
Requires-Dist: deciphon-snap<2,>=1.0.3
Requires-Dist: h3daemon>=2.0.5
Requires-Dist: loguru<1,>=0.7.2
Requires-Dist: tenacity<10,>=9.0.0
